bottleneck/__init__.py
bottleneck/_pytesttester.py
bottleneck/_version.py
bottleneck/conftest.py
bottleneck/move.cpython-311-x86_64-linux-gnu.so
bottleneck/nonreduce.cpython-311-x86_64-linux-gnu.so
bottleneck/nonreduce_axis.cpython-311-x86_64-linux-gnu.so
bottleneck/reduce.cpython-311-x86_64-linux-gnu.so
bottleneck/benchmark/__init__.py
bottleneck/benchmark/autotimeit.py
bottleneck/benchmark/bench.py
bottleneck/benchmark/bench_detailed.py
bottleneck/slow/__init__.py
bottleneck/slow/move.py
bottleneck/slow/nonreduce.py
bottleneck/slow/nonreduce_axis.py
bottleneck/slow/reduce.py
bottleneck/src/__init__.py
bottleneck/src/bn_config.py
bottleneck/src/bn_template.py
bottleneck/tests/__init__.py
bottleneck/tests/common.py
bottleneck/tests/input_modification_test.py
bottleneck/tests/list_input_test.py
bottleneck/tests/memory_test.py
bottleneck/tests/move_test.py
bottleneck/tests/nonreduce_axis_test.py
bottleneck/tests/nonreduce_test.py
bottleneck/tests/reduce_test.py
bottleneck/tests/scalar_input_test.py
bottleneck/tests/test_template.py
bottleneck/tests/util.py
bottleneck/tests/data/template_test/test_template.c
bottleneck/tests/data/template_test/truth.c
bottleneck-1.5.0.dist-info/METADATA
bottleneck-1.5.0.dist-info/WHEEL
bottleneck-1.5.0.dist-info/top_level.txt
bottleneck-1.5.0.dist-info/RECORD
bottleneck-1.5.0.dist-info/licenses/LICENSE
